README.md
setup.cfg
setup.py
cratedigger/__init__.py
cratedigger/cli.py
cratedigger.egg-info/PKG-INFO
cratedigger.egg-info/SOURCES.txt
cratedigger.egg-info/dependency_links.txt
cratedigger.egg-info/entry_points.txt
cratedigger.egg-info/requires.txt
cratedigger.egg-info/top_level.txt
cratedigger/commands/__init__.py
cratedigger/commands/sync.py
cratedigger/media/__init__.py
cratedigger/media/crate.py
cratedigger/media/library.py
cratedigger/serato/__init__.py
cratedigger/serato/crate.py
cratedigger/serato/library.py
cratedigger/util/__init__.py
cratedigger/util/io/__init__.py